{
    "key": "group_62d8654388b27",
    "title": "-- 1 -- section  --  floor selector and gallery",
    "fields": [
        {
            "key": "field_62d8686ab778e",
            "label": "Title",
            "name": "",
            "type": "message",
            "instructions": "",
            "required": 0,
            "conditional_logic": 0,
            "wrapper": {
                "width": "15",
                "class": "small-label acf-clear",
                "id": ""
            },
            "message": "",
            "new_lines": "wpautop",
            "esc_html": 0
        },
        {
            "key": "field_62d86878420a3",
            "label": "Title",
            "name": "title",
            "type": "wysiwyg",
            "instructions": "",
            "required": 0,
            "conditional_logic": 0,
            "wrapper": {
                "width": "85",
                "class": "",
                "id": ""
            },
            "default_value": "",
            "tabs": "all",
            "toolbar": "full",
            "media_upload": 1,
            "delay": 0
        },
        {
            "key": "field_62d86543b25bd",
            "label": "Floor Selector",
            "name": "",
            "type": "message",
            "instructions": "",
            "required": 0,
            "conditional_logic": 0,
            "wrapper": {
                "width": "15",
                "class": "small-label acf-clear",
                "id": ""
            },
            "message": "",
            "new_lines": "wpautop",
            "esc_html": 0
        },
        {
            "key": "field_62d8664bf5ef2",
            "label": "svg",
            "name": "svg",
            "type": "acfe_code_editor",
            "instructions": "",
            "required": 0,
            "conditional_logic": 0,
            "wrapper": {
                "width": "85",
                "class": "",
                "id": ""
            },
            "default_value": "",
            "placeholder": "",
            "mode": "text\/html",
            "lines": 1,
            "indent_unit": 4,
            "maxlength": "",
            "rows": 20,
            "max_rows": 20,
            "return_entities": 0
        },
        {
            "key": "field_62d8667362e3c",
            "label": "Floors",
            "name": "",
            "type": "message",
            "instructions": "",
            "required": 0,
            "conditional_logic": 0,
            "wrapper": {
                "width": "15",
                "class": "small-label acf-clear",
                "id": ""
            },
            "message": "",
            "new_lines": "wpautop",
            "esc_html": 0
        },
        {
            "key": "field_62d8670262fe3",
            "label": "Floors",
            "name": "floors",
            "type": "gallery",
            "instructions": "",
            "required": 0,
            "conditional_logic": 0,
            "wrapper": {
                "width": "85",
                "class": "",
                "id": ""
            },
            "return_format": "array",
            "preview_size": "medium",
            "insert": "append",
            "library": "all",
            "min": "",
            "max": "",
            "min_width": "",
            "min_height": "",
            "min_size": "",
            "max_width": "",
            "max_height": "",
            "max_size": "",
            "mime_types": ""
        },
        {
            "key": "field_62d90ae384427",
            "label": "Compass",
            "name": "compass",
            "type": "acfe_code_editor",
            "instructions": "",
            "required": 0,
            "conditional_logic": 0,
            "wrapper": {
                "width": "50",
                "class": "",
                "id": ""
            },
            "default_value": "",
            "placeholder": "",
            "mode": "text\/html",
            "lines": 1,
            "indent_unit": 4,
            "maxlength": "",
            "rows": 4,
            "max_rows": 10,
            "return_entities": 0
        },
        {
            "key": "field_62d90b1984428",
            "label": "Key",
            "name": "key",
            "type": "acfe_code_editor",
            "instructions": "",
            "required": 0,
            "conditional_logic": 0,
            "wrapper": {
                "width": "50",
                "class": "",
                "id": ""
            },
            "default_value": "",
            "placeholder": "",
            "mode": "text\/html",
            "lines": 1,
            "indent_unit": 4,
            "maxlength": "",
            "rows": 4,
            "max_rows": 10,
            "return_entities": 0
        },
        {
            "key": "field_62d90b3b84429",
            "label": "Footnote",
            "name": "",
            "type": "text",
            "instructions": "",
            "required": 0,
            "conditional_logic": 0,
            "wrapper": {
                "width": "",
                "class": "",
                "id": ""
            },
            "default_value": "",
            "placeholder": "",
            "prepend": "",
            "append": "",
            "maxlength": ""
        },
        {
            "key": "field_62d86543b25cc",
            "label": "Accordion Section",
            "name": "accordion_section",
            "type": "clone",
            "instructions": "",
            "required": 0,
            "conditional_logic": 0,
            "wrapper": {
                "width": "",
                "class": "",
                "id": ""
            },
            "clone": [
                "group_601ecc32e84b6"
            ],
            "display": "seamless",
            "layout": "block",
            "prefix_label": 0,
            "prefix_name": 0
        }
    ],
    "location": [
        [
            {
                "param": "post_type",
                "operator": "==",
                "value": "post"
            }
        ]
    ],
    "menu_order": 0,
    "position": "normal",
    "style": "default",
    "label_placement": "top",
    "instruction_placement": "label",
    "hide_on_screen": "",
    "active": false,
    "description": "",
    "show_in_rest": 0,
    "acfe_display_title": "",
    "acfe_autosync": [
        "json"
    ],
    "acfe_form": 0,
    "acfe_meta": "",
    "acfe_note": "",
    "modified": 1658395489
}